almonaut/__init__.py
almonaut/client.py
almonaut/common_validators.py
almonaut/exceptions.py
almonaut/session.py
almonaut/acquisitions/__init__.py
almonaut/acquisitions/acquisitions_models.py
almonaut/electronic_resources/__init__.py
almonaut/electronic_resources/electronic_resources_models.py
almonaut-0.2.0.dist-info/LICENSE
almonaut-0.2.0.dist-info/METADATA
almonaut-0.2.0.dist-info/WHEEL
almonaut-0.2.0.dist-info/top_level.txt
almonaut-0.2.0.dist-info/RECORD
