Metadata-Version: 2.1
Name: almonaut
Version: 0.2.0
Summary: A library to interact with the Ex Libris Alma(c) API
Author: University of Waterloo Library
Maintainer: University of Waterloo Library
License: Apache-2.0
Project-URL: Home Page, https://uwatlib.github.io/almonaut/
Project-URL: Bug Tracker, https://github.com/uwatlib/almonaut/issues
Project-URL: Changelog, https://github.com/uwatlib/almonaut/blob/master/CHANGELOG.md
Project-URL: Documentation, https://uwatlib.github.io/almonaut/
Classifier: Programming Language :: Python :: 3
Classifier: License :: OSI Approved :: Apache Software License
Classifier: Operating System :: OS Independent
Requires-Python: >=3.8
License-File: LICENSE
Requires-Dist: pydantic (>=1.10.7)
Requires-Dist: requests (>=2.28.2)
